codificador.v
module codificador(bcd, y);

    input [3:0] bcd;
    output reg [6:0] y;

    always @(bcd) begin
        case (bcd)
            4'b0000: y = 7'b1111110;
            4'b0001: y = 7'b0110000;
            4'b0010: y = 7'b1101101;
            4'b0011: y = 7'b1111001;
            4'b0100: y = 7'b0110011;
            4'b0101: y = 7'b1011011;
            4'b0110: y = 7'b1011111;
            4'b0111: y = 7'b1110000;
            4'b1000: y = 7'b1111111;
            4'b1001: y = 7'b1111011;
            4'b1010: y = 7'b1110111;
            4'b1011: y = 7'b0011111;
            4'b1100: y = 7'b1001110;
            4'b1101: y = 7'b0111101;
            4'b1110: y = 7'b1001111;
            4'b1111: y = 7'b1000111;
            default: y = 7'b0000000;
        endcase
    end
endmodule

codificador_tb.v
`timescale 1ns/1ns
`include "codificador.v"

module codificador_tb;

    reg [3:0] bcd;
    wire [6:0] y;

    codificador uut(bcd, y);

    initial begin
        $dumpfile("codificador_tb.vcd");
        $dumpvars(0, codificador_tb);

        bcd = 4'b0000; #20;
        bcd = 4'b0001; #20;
        bcd = 4'b0010; #20;
        bcd = 4'b0011; #20;
        bcd = 4'b0100; #20;
        bcd = 4'b0101; #20; 
        bcd = 4'b0110; #20; 
        bcd = 4'b0111; #20;  
        bcd = 4'b1000; #20; 
        bcd = 4'b1001; #20;
        bcd = 4'b1010; #20; 
        bcd = 4'b1011; #20; 
        bcd = 4'b1100; #20; 
        bcd = 4'b1101; #20; 
        bcd = 4'b1110; #20; 
        bcd = 4'b1111; #20; 

        $display("Teste completo");
    end

endmodule

codificador_tb.vcd
$date
	Mon Sep 23 09:11:46 2024
$end
$version
	Icarus Verilog
$end
$timescale
	1ns
$end
$scope module codificador_tb $end
$var wire 7 ! y [6:0] $end
$var reg 4 " bcd [3:0] $end
$scope module uut $end
$var wire 4 # bcd [3:0] $end
$var reg 7 $ y [6:0] $end
$upscope $end
$upscope $end
$enddefinitions $end
$comment Show the parameter values. $end
$dumpall
$end
#0
$dumpvars
b1111110 $
b0 #
b0 "
b1111110 !
$end
#20
b110000 !
b110000 $
b1 "
b1 #
#40
b1101101 !
b1101101 $
b10 "
b10 #
#60
b1111001 !
b1111001 $
b11 "
b11 #
#80
b110011 !
b110011 $
b100 "
b100 #
#100
b1011011 !
b1011011 $
b101 "
b101 #
#120
b1011111 !
b1011111 $
b110 "
b110 #
#140
b1110000 !
b1110000 $
b111 "
b111 #
#160
b1111111 !
b1111111 $
b1000 "
b1000 #
#180
b1111011 !
b1111011 $
b1001 "
b1001 #
#200
b1110111 !
b1110111 $
b1010 "
b1010 #
#220
b11111 !
b11111 $
b1011 "
b1011 #
#240
b1001110 !
b1001110 $
b1100 "
b1100 #
#260
b111101 !
b111101 $
b1101 "
b1101 #
#280
b1001111 !
b1001111 $
b1110 "
b1110 #
#300
b1000111 !
b1000111 $
b1111 "
b1111 #
