decodificador.v

module decodificador(A, E, S);

    input [2:0] A;
    input E;
    output reg [7:0] S;

    always @(A or E) begin
        if (E == 1) begin
        case (A)
            3'b000: S = 8'b00000001;
            3'b001: S = 8'b00000010;
            3'b010: S = 8'b00000100;
            3'b011: S = 8'b00001000;
            3'b100: S = 8'b00010000;
            3'b101: S = 8'b00100000;
            3'b110: S = 8'b01000000;
            3'b111: S = 8'b10000000;
        endcase
        end
        else 
            S = 8'b00000000;
        
        
    end
endmodule

decodificador_tb.v
`timescale 1ns/1ns
`include "decodificador.v"

module decodificador_tb;

    reg [2:0] A;
    reg E; 
    wire [7:0] S;

    decodificador uut(A, E, S);

    initial begin
        $dumpfile("decodificador_tb.vcd");
        $dumpvars(0, decodificador_tb);

        E = 1;
        A = 3'b000; #20;
        A = 3'b001; #20;
        A = 3'b010; #20;
        A = 3'b011; #20;
        A = 3'b100; #20;
        A = 3'b101; #20;
        A = 3'b110; #20;
        A = 3'b111; #20; 
        E = 0; #20;
        $display("Teste completo");
    end

endmodule

decodificador_tb.vcd
$date
	Mon Sep 23 10:21:46 2024
$end
$version
	Icarus Verilog
$end
$timescale
	1ns
$end
$scope module decodificador_tb $end
$var wire 8 ! S [7:0] $end
$var reg 3 " A [2:0] $end
$var reg 1 # E $end
$scope module uut $end
$var wire 3 $ A [2:0] $end
$var wire 1 # E $end
$var reg 8 % S [7:0] $end
$upscope $end
$upscope $end
$enddefinitions $end
$comment Show the parameter values. $end
$dumpall
$end
#0
$dumpvars
b1 %
b0 $
1#
b0 "
b1 !
$end
#20
b10 !
b10 %
b1 "
b1 $
#40
b100 !
b100 %
b10 "
b10 $
#60
b1000 !
b1000 %
b11 "
b11 $
#80
b10000 !
b10000 %
b100 "
b100 $
#100
b100000 !
b100000 %
b101 "
b101 $
#120
b1000000 !
b1000000 %
b110 "
b110 $
#140
b10000000 !
b10000000 %
b111 "
b111 $
#160
b0 !
b0 %
0#
